<Model xmlns="http://schemas.datacontract.org/2004/07/OpenConfigurator.Core.XmlDAL.ModelFile.DataEntities" xmlns:i="http://www.w3.org/2001/XMLSchema-instance"><Name>Unnamed Model</Name><UIOrientation>0</UIOrientation><ScaleModifier>1</ScaleModifier><Features><Feature><Identifier>Feature_0</Identifier><Name>Feature_0</Name><Attributes/><XPos>519.5</XPos><YPos>196.5</YPos></Feature><Feature><Identifier>Feature_1</Identifier><Name>Feature_1</Name><Attributes/><XPos>574.5</XPos><YPos>301.5</YPos></Feature></Features><Relations/><GroupRelations/><CompositionRules/><CustomRules/></Model>